pokebase/__init__.py
pokebase/api.py
pokebase/cache.py
pokebase/common.py
pokebase/interface.py
pokebase/loaders.py
pokebase-1.4.0.dist-info/LICENSE.txt
pokebase-1.4.0.dist-info/METADATA
pokebase-1.4.0.dist-info/WHEEL
pokebase-1.4.0.dist-info/top_level.txt
pokebase-1.4.0.dist-info/RECORD
