Metadata-Version: 2.1
Name: pokebase
Version: 1.4.0
Summary: A Python wrapper for the friendly PokeAPI database
Home-page: https://github.com/PokeAPI/pokebase
Author: Greg Hilmes
Author-email: 99hilmes.g@gmail.com
License: BSD License
Keywords: database,pokemon,wrapper
Classifier: License :: OSI Approved :: BSD License
Classifier: Programming Language :: Python :: 3.8
Classifier: Programming Language :: Python :: 3.9
Classifier: Programming Language :: Python :: 3.10
Classifier: Programming Language :: Python :: 3.11
Classifier: Programming Language :: Python :: 3.12
License-File: LICENSE.txt
Requires-Dist: requests
